{
  "grade": [
    {
      "title": "一年级一班",
      "numberId": "001",
      "students": [
        {
          "name": "一年级一班全部学生",
          "number": "001-001"
        },
        {
          "name": "一年级一班全部家长",
          "number": "001-002"
        }
      ]
    },
    {
      "title": "二年级二班",
      "numberId": "002",
      "students": [
        {
          "name": "二年级二班全部学生",
          "number": "002-001"
        },
        {
          "name": "二年级二班全部家长",
          "number": "002-002"
        }
      ]
    },
    {
      "title": "三年级三班",
      "numberId": "003",
      "students": [
        {
          "name": "三年级三班全部学生",
          "number": "003-001"
        },
        {
          "name": "三年级三班全部家长",
          "number": "003-002"
        }
      ]
    }
  ]
}
